<?xml version="1.0" encoding="UTF-8"?>
<DCOPData Simulator="hpeesofsim" Version="1.0" Time="Mo Aug 17 19:58:07 2020">
 <Controller name="DC1">
  <SweepCondition>
   <P>Ibias: 9.9999999999999998e-13</P>
  </SweepCondition>
  <DC_OPDeclaration/>
  <DC_Voltages>
   <V>0: 0.0000000000000000e+00</V>
   <V>N__11: 1.6666665720519439e-01</V>
   <V>N__2: 8.3333343030312354e-02</V>
   <V>N__3: 8.3333343030312354e-02</V>
   <V>N__4: 1.6666665715519438e-01</V>
   <V>N__5: 1.6666665715519438e-01</V>
   <V>N__7: 1.6666665720654439e-01</V>
   <V>N__8: 8.3333343030312354e-02</V>
   <V>Vdut: 1.6666665720654439e-01</V>
   <V>Vtot: 1.6666665724821106e-01</V>
   <GV>0: 0.0000000000000000e+00</GV>
  </DC_Voltages>
  <DC_PinCurrents>
   <I>Ibase: 3.7953591598148638e-20, -3.7953591598148638e-20</I>
   <I>Idut: 6.6666668554397426e-13, -6.6666668554397426e-13</I>
   <I>R2: 8.3333340228364250e-13, -8.3333340228364250e-13</I>
   <I>R3: 5.0000127495132399e-13, -5.0000127495132399e-13</I>
   <I>Rsub2: 3.3333336091345701e-13, -3.3333336091345701e-13</I>
   <I>SDD4P1: 0.0000000000000000e+00, 0.0000000000000000e+00, 0.0000000000000000e+00, 0.0000000000000000e+00, 0.0000000000000000e+00, 0.0000000000000000e+00, 0.0000000000000000e+00, 0.0000000000000000e+00</I>
   <I>SRC1: 9.9999999999999998e-13, -9.9999999999999998e-13</I>
   <I>npn1: 8.3333332927696931e-14, 3.7953591600474138e-20, -8.3333370881288527e-14</I>
   <I>pnp1: -8.3333314831233130e-14, 8.3333314074952647e-14, 7.5628048282972813e-22</I>
  </DC_PinCurrents>
  <DC_OPInstances/>
 </Controller>
</DCOPData>
